cli/__init__.py
cli/config.py
cli/ctl.py
cli/indexer.py
cli/reindex.py
cli/server.py
cli/setup.py
synapstor/__init__.py
synapstor/env_loader.py
synapstor/main.py
synapstor/mcp_server.py
synapstor/qdrant.py
synapstor/server.py
synapstor/settings.py
synapstor-1.0.0.dist-info/licenses/LICENSE
synapstor-1.0.0.dist-info/METADATA
synapstor-1.0.0.dist-info/WHEEL
synapstor-1.0.0.dist-info/entry_points.txt
synapstor-1.0.0.dist-info/top_level.txt
synapstor-1.0.0.dist-info/RECORD
