Metadata-Version: 2.4
Name: synapstor
Version: 1.0.0
Summary: An unofficial evolution of mcp-server-qdrant - Client and server for semantic storage and search
Author-email: Malindentado <contato@casheiro.com.br>
License-Expression: MIT
Project-URL: Homepage, https://github.com/casheiro/synapstor
Project-URL: Bug Tracker, https://github.com/casheiro/synapstor/issues
Requires-Python: >=3.10
License-File: LICENSE
Requires-Dist: mcp[cli]>=1.3.0
Requires-Dist: dotenv
Requires-Dist: qdrant-client>=1.3.1
Requires-Dist: fastembed>=0.6.1
Requires-Dist: sentence-transformers>=2.2.2
Requires-Dist: Unidecode>=1.3.0
Requires-Dist: docopt>=0.6.0
Requires-Dist: fastapi>=0.85.1
Requires-Dist: uvicorn>=0.19.0
Requires-Dist: langchain>=0.0.200
Requires-Dist: pydantic-settings>=2.0.0
Requires-Dist: psutil>=6.0.0
Requires-Dist: pytest>=7.4.3
Provides-Extra: fastembed
Requires-Dist: fastembed>=0.6.1; extra == "fastembed"
Provides-Extra: dev
Requires-Dist: pre-commit; extra == "dev"
Requires-Dist: black; extra == "dev"
Requires-Dist: isort; extra == "dev"
Requires-Dist: flake8; extra == "dev"
Requires-Dist: mypy; extra == "dev"
Requires-Dist: commitizen; extra == "dev"
Provides-Extra: test
Requires-Dist: pytest>=7.4.3; extra == "test"
Requires-Dist: pytest-cov>=2.12.1; extra == "test"
Requires-Dist: pytest-asyncio>=0.21.0; extra == "test"
Provides-Extra: all
Requires-Dist: fastembed>=0.6.1; extra == "all"
Requires-Dist: pre-commit; extra == "all"
Requires-Dist: black; extra == "all"
Requires-Dist: isort; extra == "all"
Requires-Dist: flake8; extra == "all"
Requires-Dist: mypy; extra == "all"
Requires-Dist: pytest>=7.4.3; extra == "all"
Requires-Dist: pytest-cov>=2.12.1; extra == "all"
Requires-Dist: pytest-asyncio>=0.21.0; extra == "all"
Requires-Dist: commitizen; extra == "all"
Dynamic: license-file
